lz4_flex_py-0.1.3.dist-info/METADATA
lz4_flex_py-0.1.3.dist-info/WHEEL
lz4_flex/__init__.py
lz4_flex/lz4_flex.abi3.so
lz4_flex_py-0.1.3.dist-info/RECORD
