Metadata-Version: 2.1
Name: lz4_flex_py
Version: 0.1.3
Summary: A Python wrapper for lz4_flex Rust crate
Project-URL: Source Code, https://github.com/imbolc/lz4_flex_py
